matrix_linalg/__init__.py
matrix_linalg/matrix_linalg.py
matrix_linalg-0.0.2.dist-info/LICENSE
matrix_linalg-0.0.2.dist-info/METADATA
matrix_linalg-0.0.2.dist-info/WHEEL
matrix_linalg-0.0.2.dist-info/top_level.txt
matrix_linalg-0.0.2.dist-info/RECORD
